stakk/__init__.py
stakk/bench_handler.py
stakk/cli_handler.py
stakk/meta_handler.py
stakk-0.1.0.dist-info/LICENSE
stakk-0.1.0.dist-info/METADATA
stakk-0.1.0.dist-info/WHEEL
stakk-0.1.0.dist-info/top_level.txt
stakk-0.1.0.dist-info/RECORD
