Metadata-Version: 2.1
Name: stakk
Version: 0.1.0
Summary: Stakk is designed to stack functions into a register, this registered stack is designed to be consumed by a stack of modular utilities.
Home-page: https://github.com/aastopher/stakk
Author: Aaron Stopher
Project-URL: Documentation, https://stakk.readthedocs.io
Project-URL: Bug Tracker, https://github.com/aastopher/stakk/issues
Keywords: agent,worker,threading,cli,utils,performance counter,benchmark
Classifier: Programming Language :: Python :: 3
Classifier: License :: OSI Approved :: MIT License
Classifier: Operating System :: OS Independent
Requires-Python: >=3.6
License-File: LICENSE
